lnwza/__init__.py
lnwza/__main__.py
lnwza/constant.py
lnwza/install.py
lnwza/main.py
lnwza/multi.py
lnwza/package.py
lnwza/profile.py
lnwza/proxy.py
lnwza/same_print.py
lnwza-0.0.19.dist-info/LICENSE.txt
lnwza-0.0.19.dist-info/METADATA
lnwza-0.0.19.dist-info/WHEEL
lnwza-0.0.19.dist-info/entry_points.txt
lnwza-0.0.19.dist-info/top_level.txt
lnwza-0.0.19.dist-info/RECORD
