Metadata-Version: 2.1
Name: lnwza
Version: 0.0.19
Summary: lnwza by hexs
Author: hexs
Author-email: zxjq97@gmail.com
License: MIT
License-File: LICENSE.txt
